genome_uploader-2.5.0.dist-info/licenses/LICENSE.md
genomeuploader/__init__.py
genomeuploader/config.py
genomeuploader/constants.py
genomeuploader/download_webin_cli.py
genomeuploader/ena.py
genomeuploader/ena_submit.py
genomeuploader/exceptions.py
genomeuploader/genome_upload.py
genomeuploader/taxon_finder.py
genome_uploader-2.5.0.dist-info/METADATA
genome_uploader-2.5.0.dist-info/WHEEL
genome_uploader-2.5.0.dist-info/entry_points.txt
genome_uploader-2.5.0.dist-info/top_level.txt
genome_uploader-2.5.0.dist-info/RECORD
